proxychecker/__init__.py
proxychecker/app.py
pptChecker-0.3.10.dist-info/LICENSE
pptChecker-0.3.10.dist-info/METADATA
pptChecker-0.3.10.dist-info/WHEEL
pptChecker-0.3.10.dist-info/entry_points.txt
pptChecker-0.3.10.dist-info/top_level.txt
pptChecker-0.3.10.dist-info/RECORD
